ckl_psm/__init__.py
ckl_psm/ckl_pcfg.py
ckl_psm/fast_bpe_sim.py
ckl_psm/monte_carlo_lib.py
ckl_psm/resources/bpemodel.pickle
ckl_psm/resources/dangerous_chunks.pickle
ckl_psm/resources/intermediate_results.pickle
ckl_psm/resources/monte_carlo_sample.pickle
ckl_psm-1.2.data/data/bpemodel.pickle
ckl_psm-1.2.data/data/dangerous_chunks.pickle
ckl_psm-1.2.data/data/intermediate_results.pickle
ckl_psm-1.2.data/data/monte_carlo_sample.pickle
ckl_psm-1.2.dist-info/METADATA
ckl_psm-1.2.dist-info/WHEEL
ckl_psm-1.2.dist-info/top_level.txt
ckl_psm-1.2.dist-info/RECORD
