Metadata-Version: 2.1
Name: ckl-psm
Version: 1.2
Summary: A password strength meter (PSM) with CKL_PCFG model
Home-page: https://github.com/snow0011/CKL_PSM
Author: snow0011
Author-email: daslab@163.com
License: UNKNOWN
Platform: UNKNOWN
Classifier: Programming Language :: Python :: 3
Classifier: License :: OSI Approved :: MIT License
Classifier: Operating System :: OS Independent
